fvmd/__init__.py
fvmd/__main__.py
fvmd/extract_motion_features.py
fvmd/frechet_distance.py
fvmd/fvmd.py
fvmd/keypoint_tracking.py
fvmd/datasets/__init__.py
fvmd/datasets/video_datasets.py
fvmd/nets/__init__.py
fvmd/nets/pips2.py
fvmd/utils/__init__.py
fvmd/utils/basic.py
fvmd/utils/geom.py
fvmd/utils/improc.py
fvmd/utils/misc.py
fvmd/utils/samp.py
fvmd/utils/saverloader.py
fvmd/utils/vox.py
fvmd-1.0.0.dist-info/LICENSE.txt
fvmd-1.0.0.dist-info/METADATA
fvmd-1.0.0.dist-info/WHEEL
fvmd-1.0.0.dist-info/entry_points.txt
fvmd-1.0.0.dist-info/top_level.txt
fvmd-1.0.0.dist-info/RECORD
