Metadata-Version: 2.1
Name: fvmd
Version: 1.0.0
Summary: Frechet Video Motion Distance
License: Apache Software License 2.0
Project-URL: Source, https://github.com/ljh0v0/FVMD-frechet-video-motion-distance
License-File: LICENSE.txt
Requires-Dist: torch
Requires-Dist: torchvision
Requires-Dist: loguru
Requires-Dist: einops ==0.6.1
Requires-Dist: scikit-learn ==1.3.0
Requires-Dist: matplotlib ==3.7.3
Requires-Dist: opencv-python ==4.8.0.76
Requires-Dist: scikit-image ==0.21.0
Requires-Dist: albumentations ==1.3.1
Requires-Dist: tensorboardX ==2.6.2.2
Requires-Dist: fire ==0.5.0
Requires-Dist: moviepy ==1.0.3
Requires-Dist: prettytable ==3.9.0
Requires-Dist: scipy ==1.10.1
